Metadata-Version: 2.1
Name: neon-stt-plugin-google-cloud-beta
Version: 0.2.4
Summary: A Google stt plugin for Neon
Home-page: https://github.com/NeonGeckoCom/neon-stt-plugin-google_cloud_beta
Author: Neongecko
Author-email: developers@neon.ai
License: NeonAI License v1.0
Keywords: mycroft plugin stt
Platform: UNKNOWN
Classifier: Intended Audience :: Developers
Classifier: Topic :: Text Processing :: Linguistic
Classifier: Programming Language :: Python :: 3.6
Requires-Dist: google (~=2.0.3)
Requires-Dist: google-cloud-speech (~=2.4.0)
Requires-Dist: google-api-python-client (==1.6.4)
Requires-Dist: pydub
Requires-Dist: SpeechRecognition (~=3.8.1)
Requires-Dist: ovos-plugin-manager
Requires-Dist: neon-utils (~=0.14)
